llama_index/instrumentation/agentops/BUILD
llama_index/instrumentation/agentops/__init__.py
llama_index/instrumentation/agentops/base.py
llama_index_instrumentation_agentops-0.1.0.dist-info/METADATA
llama_index_instrumentation_agentops-0.1.0.dist-info/WHEEL
llama_index_instrumentation_agentops-0.1.0.dist-info/RECORD
