Metadata-Version: 2.1
Name: llama-index-instrumentation-agentops
Version: 0.1.0
Summary: llama-index instrumentation agentops integration
License: MIT
Author: Your Name
Author-email: you@example.com
Requires-Python: >=3.8.1,<4.0
Classifier: License :: OSI Approved :: MIT License
Classifier: Programming Language :: Python :: 3
Classifier: Programming Language :: Python :: 3.9
Classifier: Programming Language :: Python :: 3.10
Classifier: Programming Language :: Python :: 3.11
Requires-Dist: agentops (>=0.2.2,<0.3.0)
Requires-Dist: llama-index-core (>=0.10.0,<0.11.0)
